raster2dggs/__init__.py
raster2dggs/cli.py
raster2dggs/cli_factory.py
raster2dggs/common.py
raster2dggs/constants.py
raster2dggs/indexerfactory.py
raster2dggs/indexers/__init__.py
raster2dggs/indexers/a5rasterindexer.py
raster2dggs/indexers/dggalrasterindexer.py
raster2dggs/indexers/geohashrasterindexer.py
raster2dggs/indexers/h3rasterindexer.py
raster2dggs/indexers/maidenheadrasterindexer.py
raster2dggs/indexers/rasterindexer.py
raster2dggs/indexers/rhprasterindexer.py
raster2dggs/indexers/s2rasterindexer.py
raster2dggs/interfaces.py
raster2dggs-0.7.1.dist-info/METADATA
raster2dggs-0.7.1.dist-info/WHEEL
raster2dggs-0.7.1.dist-info/entry_points.txt
raster2dggs-0.7.1.dist-info/licenses/COPYING
raster2dggs-0.7.1.dist-info/licenses/COPYING.LESSER
raster2dggs-0.7.1.dist-info/RECORD
