Metadata-Version: 2.4
Name: raster2dggs
Version: 0.7.1
Summary: 
License: LGPL-3.0-or-later
License-File: COPYING
License-File: COPYING.LESSER
Keywords: dggs,raster,h3,rHEALPix,cli
Author: James Ardo
Author-email: ardoj@landcareresearch.co.nz
Maintainer: Richard Law
Maintainer-email: lawr@landcareresearch.co.nz
Requires-Python: >=3.11,<4.0
Classifier: License :: OSI Approved :: GNU Lesser General Public License v3 or later (LGPLv3+)
Classifier: Programming Language :: Python :: 3
Classifier: Programming Language :: Python :: 3.11
Classifier: Programming Language :: Python :: 3.12
Classifier: Programming Language :: Python :: 3.13
Classifier: Programming Language :: Python :: 3.14
Classifier: Topic :: Scientific/Engineering
Classifier: Topic :: Scientific/Engineering :: GIS
Classifier: Topic :: Scientific/Engineering :: Image Processing
Classifier: Topic :: Scientific/Engineering :: Information Analysis
Requires-Dist: boto3 (>=1,<2)
Requires-Dist: click (>=8.1,<9.0)
Requires-Dist: click-log (>=0.4,<0.5)
Requires-Dist: dask (>=2025.1,<2026.0)
Requires-Dist: dask-expr (>=2,<3)
Requires-Dist: dask-geopandas (>=0.5,<0.6)
Requires-Dist: dggal (>=0.0.6,<0.0.7)
Requires-Dist: gdal (>=3.8,<4.0)
Requires-Dist: geoarrow-pyarrow (>=0.2.0,<0.3.0)
Requires-Dist: geopandas (>=1.0,<2.0)
Requires-Dist: h3pandas (>=0.3,<0.4)
Requires-Dist: maidenhead (>=1.8,<2.0)
Requires-Dist: numpy (>=2,<3)
Requires-Dist: pya5 (>=0.5,<0.6)
Requires-Dist: pyarrow (>=20.0,<21.0)
Requires-Dist: python-geohash (>=0.8,<0.9)
Requires-Dist: rasterio (>=1.4,<2.0)
Requires-Dist: rhealpixdggs (>=0.5,<0.6)
Requires-Dist: rhppandas (>=0.1,<0.2)
Requires-Dist: rioxarray (>=0.19,<0.20)
Requires-Dist: s2sphere (>=0.2,<0.3)
Requires-Dist: tqdm (>=4,<5)
Project-URL: Repository, https://github.com/manaakiwhenua/raster2dggs
